prx_pyaec/__init__.py
prx_pyaec/libaec.dylib
prx_pyaec-2.0.6.dist-info/METADATA
prx_pyaec-2.0.6.dist-info/WHEEL
prx_pyaec-2.0.6.dist-info/RECORD
