Metadata-Version: 2.4
Name: prx_pyaec
Version: 2.0.6
Summary: PRX Acoustic echo cancellation with reset
Author-email: wnm3 <wnmills3@gmail.com>, thewh1teagle <61390950+thewh1teagle@users.noreply.github.com>
Requires-Python: >=3.11
